[{"suites": 1, "vagas": 2, "quartos": 3, "tipo": 1, "valor": "R$ 1.500", "bairro": "MORUMBI", "cidade": "Sao Paulo", "area": 98, "id": 7299616, "subtipo": 1}, {"suites": 0, "vagas": 1, "quartos": 2, "tipo": 1, "valor": "R$ 3.500", "bairro": "MOEMA", "cidade": "Sao Paulo", "area": 92, "id": 9517571, "subtipo": 2}, {"suites": 1, "vagas": 2, "quartos": 2, "tipo": 1, "valor": "R$ 3.500", "bairro": "MOEMA", "cidade": "Sao Paulo", "area": 80, "id": 9577486, "subtipo": 2}, {"suites": 1, "vagas": 2, "quartos": 3, "tipo": 1, "valor": "R$ 4.500", "bairro": "ITAIM BIBI", "cidade": "Sao Paulo", "area": 190, "id": 9046378, "subtipo": 1}, {"suites": 0, "vagas": 1, "quartos": 1, "tipo": 1, "valor": "R$ 1.300", "bairro": "CAMPOS EL\u00cdSEOS", "cidade": "Sao Paulo", "area": 33, "id": 8646029, "subtipo": 2}, {"suites": 1, "vagas": 1, "quartos": 3, "tipo": 1, "valor": "R$ 2.023", "bairro": "JD MARAJOARA", "cidade": "Sao Paulo", "area": 72, "id": 8867303, "subtipo": 1}, {"suites": 1, "vagas": 2, "quartos": 4, "tipo": 1, "valor": "R$ 3.500", "bairro": "BROOKLIN", "cidade": "Sao Paulo", "area": 150, "id": 5247018, "subtipo": 2}, {"suites": 0, "vagas": 1, "quartos": 2, "tipo": 1, "valor": "R$ 3.000", "bairro": "CONSOLA\u00c7\u00c3O", "cidade": "Sao Paulo", "area": 110, "id": 9393264, "subtipo": 4}, {"suites": 0, "vagas": 1, "quartos": 2, "tipo": 1, "valor": "R$ 2.400", "bairro": "BARRA FUNDA", "cidade": "Sao Paulo", "area": 52, "id": 9217885, "subtipo": 1}, {"suites": 1, "vagas": 3, "quartos": 3, "tipo": 1, "valor": "R$ 7.000", "bairro": "JD PAULISTA", "cidade": "Sao Paulo", "area": 155, "id": 8646403, "subtipo": 2}, {"suites": 1, "vagas": 2, "quartos": 3, "tipo": 1, "valor": "R$ 7.500", "bairro": "JD PAULISTANO", "cidade": "Sao Paulo", "area": 180, "id": 8732128, "subtipo": 1}, {"suites": 1, "vagas": 1, "quartos": 3, "tipo": 1, "valor": "R$ 2.000", "bairro": "CH KLABIN", "cidade": "Sao Paulo", "area": 68, "id": 7953068, "subtipo": 4}, {"suites": 0, "vagas": 1, "quartos": 2, "tipo": 1, "valor": "R$ 2.500", "bairro": "PINHEIROS", "cidade": "Sao Paulo", "area": 75, "id": 9082719, "subtipo": 4}, {"suites": 1, "vagas": 2, "quartos": 1, "tipo": 1, "valor": "R$ 2.300", "bairro": "MORUMBI", "cidade": "Sao Paulo", "area": 58, "id": 6594947, "subtipo": 1}, {"suites": 1, "vagas": 1, "quartos": 3, "tipo": 1, "valor": "R$ 4.000", "bairro": "JD PAULISTA", "cidade": "Sao Paulo", "area": 130, "id": 9458350, "subtipo": 2}, {"suites": 4, "vagas": 4, "quartos": 4, "tipo": 1, "valor": "R$ 15.000", "bairro": "CAMPO BELO", "cidade": "Sao Paulo", "area": 276, "id": 9381915, "subtipo": 1}, {"suites": 1, "vagas": 1, "quartos": 1, "tipo": 1, "valor": "R$ 6.000", "bairro": "ITAIM BIBI", "cidade": "Sao Paulo", "area": 90, "id": 9393167, "subtipo": 4}, {"suites": 2, "vagas": 2, "quartos": 2, "tipo": 1, "valor": "R$ 8.400", "bairro": "JD PAULISTA", "cidade": "Sao Paulo", "area": 65, "id": 7634088, "subtipo": 2}]