[{"suites": 2, "vagas": 2, "quartos": 4, "tipo": 1, "valor": "R$ 8.000", "bairro": "CAMPO BELO", "cidade": "Sao Paulo", "area": 204, "id": 7358685, "subtipo": 2}, {"suites": 3, "vagas": 4, "quartos": 4, "tipo": 1, "valor": "R$ 15.000", "bairro": "VL MADALENA", "cidade": "Sao Paulo", "area": 261, "id": 9091706, "subtipo": 2}, {"suites": 1, "vagas": 2, "quartos": 3, "tipo": 1, "valor": "R$ 3.800", "bairro": "VL LEOPOLDINA", "cidade": "Sao Paulo", "area": 93, "id": 8766988, "subtipo": 1}, {"suites": 1, "vagas": 2, "quartos": 3, "tipo": 1, "valor": "R$ 9.000", "bairro": "JD PAULISTA", "cidade": "Sao Paulo", "area": 120, "id": 9593746, "subtipo": 2}, {"suites": 0, "vagas": 0, "quartos": 2, "tipo": 1, "valor": "R$ 1.350", "bairro": "BOM RETIRO", "cidade": "Sao Paulo", "area": 110, "id": 9474679, "subtipo": 4}, {"suites": 0, "vagas": 1, "quartos": 3, "tipo": 1, "valor": "R$ 2.100", "bairro": "BUTANT\u00c3", "cidade": "Sao Paulo", "area": 60, "id": 9533515, "subtipo": 1}, {"suites": 0, "vagas": 1, "quartos": 2, "tipo": 1, "valor": "R$ 2.500", "bairro": "MOEMA", "cidade": "Sao Paulo", "area": 80, "id": 7400811, "subtipo": 1}, {"suites": 1, "vagas": 1, "quartos": 2, "tipo": 1, "valor": "R$ 2.100", "bairro": "POMP\u00c9IA", "cidade": "Sao Paulo", "area": 74, "id": 9434964, "subtipo": 1}, {"suites": 2, "vagas": 2, "quartos": 3, "tipo": 1, "valor": "R$ 2.400", "bairro": "VL MASCOTE", "cidade": "Sao Paulo", "area": 100, "id": 8736888, "subtipo": 4}, {"suites": 3, "vagas": 4, "quartos": 3, "tipo": 1, "valor": "R$ 26.000", "bairro": "MOEMA", "cidade": "Sao Paulo", "area": 320, "id": 8830377, "subtipo": 1}, {"suites": 0, "vagas": 1, "quartos": 1, "tipo": 1, "valor": "R$ 1.150", "bairro": "BELA VISTA", "cidade": "Sao Paulo", "area": 45, "id": 9260964, "subtipo": 1}, {"suites": 3, "vagas": 3, "quartos": 4, "tipo": 1, "valor": "R$ 4.000", "bairro": "PERDIZES", "cidade": "Sao Paulo", "area": 205, "id": 9260915, "subtipo": 1}, {"suites": 1, "vagas": 2, "quartos": 2, "tipo": 1, "valor": "R$ 8.000", "bairro": "VL NOVA CONCEI\u00c7\u00c3O", "cidade": "Sao Paulo", "area": 78, "id": 8841506, "subtipo": 2}, {"suites": 0, "vagas": 1, "quartos": 2, "tipo": 1, "valor": "R$ 2.700", "bairro": "HIGIEN\u00d3POLIS", "cidade": "Sao Paulo", "area": 107, "id": 9153761, "subtipo": 2}, {"suites": 1, "vagas": 1, "quartos": 3, "tipo": 1, "valor": "R$ 3.803", "bairro": "HIGIEN\u00d3POLIS", "cidade": "Sao Paulo", "area": 176, "id": 9301823, "subtipo": 4}, {"suites": 4, "vagas": 4, "quartos": 4, "tipo": 1, "valor": "R$ 12.000", "bairro": "MOEMA", "cidade": "Sao Paulo", "area": 250, "id": 9518618, "subtipo": 2}, {"suites": 0, "vagas": 1, "quartos": 1, "tipo": 1, "valor": "R$ 1.190", "bairro": "CAMBUCI", "cidade": "Sao Paulo", "area": 35, "id": 8934547, "subtipo": 2}, {"suites": 0, "vagas": 1, "quartos": 1, "tipo": 1, "valor": "R$ 950", "bairro": "CAMBUCI", "cidade": "Sao Paulo", "area": 60, "id": 5838079, "subtipo": 1}]