[{"suites": 1, "vagas": 2, "quartos": 3, "tipo": 1, "valor": "R$ 5.500", "bairro": "JD PAULISTA", "cidade": "Sao Paulo", "area": 140, "id": 8882915, "subtipo": 4}, {"suites": 4, "vagas": 4, "quartos": 4, "tipo": 1, "valor": "R$ 7.000", "bairro": "STA CEC\u00cdLIA", "cidade": "Sao Paulo", "area": 203, "id": 9393099, "subtipo": 4}, {"suites": 1, "vagas": 2, "quartos": 3, "tipo": 1, "valor": "R$ 2.800", "bairro": "CAMPO BELO", "cidade": "Sao Paulo", "area": 120, "id": 9612397, "subtipo": 1}, {"suites": 0, "vagas": 1, "quartos": 1, "tipo": 1, "valor": "R$ 1.600", "bairro": "CAMPO LIMPO", "cidade": "Sao Paulo", "area": 40, "id": 9285044, "subtipo": 1}, {"suites": 1, "vagas": 1, "quartos": 1, "tipo": 1, "valor": "R$ 2.800", "bairro": "VL OL\u00cdMPIA", "cidade": "Sao Paulo", "area": 43, "id": 8934235, "subtipo": 2}, {"suites": 0, "vagas": 1, "quartos": 3, "tipo": 1, "valor": "R$ 3.500", "bairro": "HIGIEN\u00d3POLIS", "cidade": "Sao Paulo", "area": 113, "id": 9207617, "subtipo": 1}, {"suites": 0, "vagas": 1, "quartos": 2, "tipo": 1, "valor": "R$ 2.000", "bairro": "MIRAND\u00d3POLIS", "cidade": "Sao Paulo", "area": 80, "id": 8360919, "subtipo": 1}, {"suites": 0, "vagas": 0, "quartos": 2, "tipo": 1, "valor": "R$ 1.700", "bairro": "VL MARIANA", "cidade": "Sao Paulo", "area": 80, "id": 4793239, "subtipo": 4}, {"suites": 0, "vagas": 1, "quartos": 3, "tipo": 1, "valor": "R$ 1.200", "bairro": "VL MASCOTE", "cidade": "Sao Paulo", "area": 75, "id": 9171893, "subtipo": 2}, {"suites": 0, "vagas": 1, "quartos": 3, "tipo": 1, "valor": "R$ 2.990", "bairro": "PLANALTO PAULISTA", "cidade": "Sao Paulo", "area": 130, "id": 9640020, "subtipo": 2}, {"suites": 1, "vagas": 1, "quartos": 3, "tipo": 1, "valor": "R$ 2.000", "bairro": "VL LEOPOLDINA", "cidade": "Sao Paulo", "area": 72, "id": 8940795, "subtipo": 2}, {"suites": 1, "vagas": 2, "quartos": 2, "tipo": 1, "valor": "R$ 2.300", "bairro": "VL PRUDENTE", "cidade": "Sao Paulo", "area": 64, "id": 9413978, "subtipo": 4}, {"suites": 0, "vagas": 1, "quartos": 3, "tipo": 1, "valor": "R$ 1.900", "bairro": "JD MARAJOARA", "cidade": "Sao Paulo", "area": 59, "id": 9475153, "subtipo": 1}, {"suites": 1, "vagas": 2, "quartos": 2, "tipo": 1, "valor": "R$ 6.000", "bairro": "JD AM\u00c9RICA", "cidade": "Sao Paulo", "area": 135, "id": 9475277, "subtipo": 2}, {"suites": 3, "vagas": 3, "quartos": 3, "tipo": 1, "valor": "R$ 12.500", "bairro": "INDIAN\u00d3POLIS", "cidade": "Sao Paulo", "area": 240, "id": 6024779, "subtipo": 1}, {"suites": 2, "vagas": 4, "quartos": 4, "tipo": 1, "valor": "R$ 25.000", "bairro": "JD AM\u00c9RICA", "cidade": "Sao Paulo", "area": 370, "id": 9622209, "subtipo": 1}, {"suites": 0, "vagas": 2, "quartos": 3, "tipo": 1, "valor": "R$ 2.500", "bairro": "JD MARAJOARA", "cidade": "Sao Paulo", "area": 78, "id": 6512799, "subtipo": 2}, {"suites": 0, "vagas": 1, "quartos": 2, "tipo": 1, "valor": "R$ 1.200", "bairro": "JD ESMERALDA", "cidade": "Sao Paulo", "area": 58, "id": 7485052, "subtipo": 1}]