[{"suites": 1, "vagas": 1, "quartos": 2, "tipo": 1, "valor": "R$ 2.500", "bairro": "CH KLABIN", "cidade": "Sao Paulo", "area": 70, "id": 2976823, "subtipo": 1}, {"suites": 0, "vagas": 2, "quartos": 2, "tipo": 1, "valor": "R$ 2.600", "bairro": "JD PAULISTA", "cidade": "Sao Paulo", "area": 56, "id": 9563930, "subtipo": 2}, {"suites": 1, "vagas": 1, "quartos": 3, "tipo": 1, "valor": "R$ 4.200", "bairro": "PINHEIROS", "cidade": "Sao Paulo", "area": 139, "id": 9120946, "subtipo": 4}, {"suites": 0, "vagas": 1, "quartos": 2, "tipo": 1, "valor": "R$ 1.800", "bairro": "VL MASCOTE", "cidade": "Sao Paulo", "area": 60, "id": 9165568, "subtipo": 1}, {"suites": 1, "vagas": 1, "quartos": 2, "tipo": 1, "valor": "R$ 2.300", "bairro": "MOOCA", "cidade": "Sao Paulo", "area": 64, "id": 6502699, "subtipo": 1}, {"suites": 1, "vagas": 1, "quartos": 3, "tipo": 1, "valor": "R$ 4.500", "bairro": "Ch\u00e1cara Santo Ant\u00f4nio", "cidade": "Sao Paulo", "area": 114, "id": 9289632, "subtipo": 4}, {"suites": 0, "vagas": 1, "quartos": 1, "tipo": 1, "valor": "R$ 1.800", "bairro": "BELA VISTA", "cidade": "Sao Paulo", "area": 32, "id": 3351004, "subtipo": 1}, {"suites": 0, "vagas": 1, "quartos": 2, "tipo": 1, "valor": "R$ 1.900", "bairro": "CAMPO GRANDE", "cidade": "Sao Paulo", "area": 50, "id": 9369209, "subtipo": 4}, {"suites": 1, "vagas": 2, "quartos": 3, "tipo": 1, "valor": "R$ 2.500", "bairro": "SA\u00daDE", "cidade": "Sao Paulo", "area": 80, "id": 8569094, "subtipo": 1}, {"suites": 0, "vagas": 1, "quartos": 2, "tipo": 1, "valor": "R$ 1.500", "bairro": "Vila Formosa", "cidade": "Sao Paulo", "area": 56, "id": 9615043, "subtipo": 4}, {"suites": 1, "vagas": 1, "quartos": 1, "tipo": 1, "valor": "R$ 3.000", "bairro": "ITAIM BIBI", "cidade": "Sao Paulo", "area": 55, "id": 7132212, "subtipo": 1}, {"suites": 4, "vagas": 4, "quartos": 4, "tipo": 1, "valor": "R$ 30.000", "bairro": "MOEMA", "cidade": "Sao Paulo", "area": 367, "id": 8892501, "subtipo": 2}, {"suites": 1, "vagas": 1, "quartos": 3, "tipo": 1, "valor": "R$ 2.200", "bairro": "JABAQUARA", "cidade": "Sao Paulo", "area": 67, "id": 8987685, "subtipo": 1}, {"suites": 1, "vagas": 2, "quartos": 2, "tipo": 1, "valor": "R$ 1.700", "bairro": "SA\u00daDE", "cidade": "Sao Paulo", "area": 60, "id": 7857161, "subtipo": 4}, {"suites": 0, "vagas": 1, "quartos": 2, "tipo": 1, "valor": "R$ 1.000", "bairro": "VL IRM\u00c3OS ARNONI", "cidade": "Sao Paulo", "area": 59, "id": 8775109, "subtipo": 2}, {"suites": 0, "vagas": 1, "quartos": 2, "tipo": 1, "valor": "R$ 3.000", "bairro": "VL NOVA CONCEI\u00c7\u00c3O", "cidade": "Sao Paulo", "area": 58, "id": 5732681, "subtipo": 1}, {"suites": 3, "vagas": 2, "quartos": 3, "tipo": 1, "valor": "R$ 6.500", "bairro": "MOEMA", "cidade": "Sao Paulo", "area": 134, "id": 9392811, "subtipo": 4}, {"suites": 3, "vagas": 5, "quartos": 3, "tipo": 1, "valor": "R$ 9.000", "bairro": "JD ANALIA FRANCO", "cidade": "Sao Paulo", "area": 244, "id": 6576371, "subtipo": 1}]