[{"suites": 0, "vagas": 0, "quartos": 1, "tipo": 1, "valor": "R$ 1.900", "bairro": "VL MARIANA", "cidade": "Sao Paulo", "area": 35, "id": 9219098, "subtipo": 2}, {"suites": 0, "vagas": 1, "quartos": 2, "tipo": 1, "valor": "R$ 1.700", "bairro": "VL MASCOTE", "cidade": "Sao Paulo", "area": 60, "id": 7948652, "subtipo": 1}, {"suites": 1, "vagas": 1, "quartos": 3, "tipo": 1, "valor": "R$ 4.000", "bairro": "HIGIEN\u00d3POLIS", "cidade": "Sao Paulo", "area": 130, "id": 9109262, "subtipo": 1}, {"suites": 1, "vagas": 2, "quartos": 3, "tipo": 1, "valor": "R$ 3.300", "bairro": "VL POMP\u00c9IA", "cidade": "Sao Paulo", "area": 127, "id": 9550396, "subtipo": 1}, {"suites": 3, "vagas": 4, "quartos": 3, "tipo": 1, "valor": "R$ 22.000", "bairro": "VL ROMANA", "cidade": "Sao Paulo", "area": 330, "id": 7330522, "subtipo": 1}, {"suites": 0, "vagas": 1, "quartos": 2, "tipo": 1, "valor": "R$ 2.500", "bairro": "SA\u00daDE", "cidade": "Sao Paulo", "area": 90, "id": 9401609, "subtipo": 4}, {"suites": 2, "vagas": 5, "quartos": 5, "tipo": 1, "valor": "R$ 7.000", "bairro": "SANTANA", "cidade": "Sao Paulo", "area": 329, "id": 6487947, "subtipo": 4}, {"suites": 1, "vagas": 2, "quartos": 3, "tipo": 1, "valor": "R$ 2.990", "bairro": "BOSQUE DA SA\u00daDE", "cidade": "Sao Paulo", "area": 92, "id": 9561414, "subtipo": 2}, {"suites": 0, "vagas": 1, "quartos": 2, "tipo": 1, "valor": "R$ 2.000", "bairro": "PERDIZES", "cidade": "Sao Paulo", "area": 86, "id": 9610282, "subtipo": 4}, {"suites": 1, "vagas": 2, "quartos": 4, "tipo": 1, "valor": "R$ 5.000", "bairro": "MOEMA", "cidade": "Sao Paulo", "area": 110, "id": 8876563, "subtipo": 1}, {"suites": 0, "vagas": 0, "quartos": 1, "tipo": 1, "valor": "R$ 1.800", "bairro": "PERDIZES", "cidade": "Sao Paulo", "area": 45, "id": 7365687, "subtipo": 1}, {"suites": 1, "vagas": 2, "quartos": 2, "tipo": 1, "valor": "R$ 12.000", "bairro": "VL NOVA CONCEI\u00c7\u00c3O", "cidade": "Sao Paulo", "area": 78, "id": 8361850, "subtipo": 2}, {"suites": 0, "vagas": 1, "quartos": 3, "tipo": 1, "valor": "R$ 1.500", "bairro": "FREGUESIA DO \u00d3", "cidade": "Sao Paulo", "area": 85, "id": 9195038, "subtipo": 1}, {"suites": 0, "vagas": 1, "quartos": 3, "tipo": 1, "valor": "R$ 3.000", "bairro": "HIGIEN\u00d3POLIS", "cidade": "Sao Paulo", "area": 126, "id": 8723949, "subtipo": 2}, {"suites": 1, "vagas": 2, "quartos": 3, "tipo": 1, "valor": "R$ 1.800", "bairro": "JD PERI PERI", "cidade": "Sao Paulo", "area": 76, "id": 9458424, "subtipo": 4}, {"suites": 4, "vagas": 4, "quartos": 4, "tipo": 1, "valor": "R$ 12.000", "bairro": "VL CORDEIRO", "cidade": "Sao Paulo", "area": 520, "id": 5339114, "subtipo": 4}, {"suites": 0, "vagas": 2, "quartos": 3, "tipo": 1, "valor": "R$ 3.350", "bairro": "MOEMA", "cidade": "Sao Paulo", "area": 80, "id": 9446788, "subtipo": 1}, {"suites": 2, "vagas": 4, "quartos": 4, "tipo": 1, "valor": "R$ 7.500", "bairro": "TATUAP\u00c9", "cidade": "Sao Paulo", "area": 225, "id": 9570311, "subtipo": 4}]