[{"suites": 0, "vagas": 1, "quartos": 2, "tipo": 1, "valor": "R$ 1.700", "bairro": "VL LAGEADO", "cidade": "Sao Paulo", "area": 58, "id": 7088049, "subtipo": 2}, {"suites": 3, "vagas": 2, "quartos": 3, "tipo": 1, "valor": "R$ 3.000", "bairro": "TATUAP\u00c9", "cidade": "Sao Paulo", "area": 186, "id": 7592423, "subtipo": 1}, {"suites": 1, "vagas": 1, "quartos": 2, "tipo": 1, "valor": "R$ 2.700", "bairro": "MOEMA", "cidade": "Sao Paulo", "area": 61, "id": 8968988, "subtipo": 2}, {"suites": 0, "vagas": 1, "quartos": 2, "tipo": 1, "valor": "R$ 2.400", "bairro": "VL MARIANA", "cidade": "Sao Paulo", "area": 55, "id": 9612371, "subtipo": 4}, {"suites": 0, "vagas": 2, "quartos": 3, "tipo": 1, "valor": "R$ 12.000", "bairro": "JARDINS", "cidade": "Sao Paulo", "area": 251, "id": 7196049, "subtipo": 1}, {"suites": 1, "vagas": 1, "quartos": 2, "tipo": 1, "valor": "R$ 3.800", "bairro": "JD PAULISTANO", "cidade": "Sao Paulo", "area": 80, "id": 7770671, "subtipo": 2}, {"suites": 1, "vagas": 2, "quartos": 3, "tipo": 1, "valor": "R$ 8.000", "bairro": "VL NOVA CONCEI\u00c7\u00c3O", "cidade": "Sao Paulo", "area": 140, "id": 6446400, "subtipo": 2}, {"suites": 1, "vagas": 1, "quartos": 3, "tipo": 1, "valor": "R$ 1.900", "bairro": "MORUMBI", "cidade": "Sao Paulo", "area": 67, "id": 8523714, "subtipo": 2}, {"suites": 1, "vagas": 2, "quartos": 3, "tipo": 1, "valor": "R$ 3.500", "bairro": "PERDIZES", "cidade": "Sao Paulo", "area": 136, "id": 7576300, "subtipo": 1}, {"suites": 0, "vagas": 0, "quartos": 2, "tipo": 1, "valor": "R$ 1.100", "bairro": "TATUAP\u00c9", "cidade": "Sao Paulo", "area": 100, "id": 7437143, "subtipo": 2}, {"suites": 3, "vagas": 7, "quartos": 3, "tipo": 1, "valor": "R$ 8.800", "bairro": "ALTO DA LAPA", "cidade": "Sao Paulo", "area": 140, "id": 7461530, "subtipo": 2}, {"suites": 2, "vagas": 2, "quartos": 2, "tipo": 1, "valor": "R$ 3.700", "bairro": "BARRA FUNDA", "cidade": "Sao Paulo", "area": 127, "id": 8473565, "subtipo": 2}, {"suites": 1, "vagas": 2, "quartos": 2, "tipo": 1, "valor": "R$ 1.200", "bairro": "MORUMBI", "cidade": "Sao Paulo", "area": 74, "id": 9034133, "subtipo": 4}, {"suites": 0, "vagas": 1, "quartos": 1, "tipo": 1, "valor": "R$ 2.200", "bairro": "CAMPO BELO", "cidade": "Sao Paulo", "area": 53, "id": 8996245, "subtipo": 4}, {"suites": 0, "vagas": 1, "quartos": 3, "tipo": 1, "valor": "R$ 1.900", "bairro": "INTERLAGOS", "cidade": "Sao Paulo", "area": 64, "id": 9314504, "subtipo": 2}, {"suites": 1, "vagas": 2, "quartos": 3, "tipo": 1, "valor": "R$ 2.650", "bairro": "ALTO DA BOA VISTA", "cidade": "Sao Paulo", "area": 87, "id": 3792051, "subtipo": 2}, {"suites": 0, "vagas": 1, "quartos": 1, "tipo": 1, "valor": "R$ 1.500", "bairro": "LIBERDADE", "cidade": "Sao Paulo", "area": 40, "id": 9222722, "subtipo": 1}, {"suites": 0, "vagas": 1, "quartos": 1, "tipo": 1, "valor": "R$ 2.500", "bairro": "VL MADALENA", "cidade": "Sao Paulo", "area": 46, "id": 6076072, "subtipo": 2}]