[{"suites": 3, "vagas": 4, "quartos": 3, "tipo": 1, "valor": "R$ 15.000", "bairro": "BROOKLIN NOVO", "cidade": "Sao Paulo", "area": 205, "id": 7327725, "subtipo": 2}, {"suites": 1, "vagas": 1, "quartos": 2, "tipo": 1, "valor": "R$ 2.000", "bairro": "TATUAP\u00c9", "cidade": "Sao Paulo", "area": 73, "id": 8654987, "subtipo": 1}, {"suites": 1, "vagas": 1, "quartos": 2, "tipo": 1, "valor": "R$ 1.750", "bairro": "PORTAL DO MORUMBI", "cidade": "Sao Paulo", "area": 68, "id": 7795338, "subtipo": 2}, {"suites": 0, "vagas": 1, "quartos": 2, "tipo": 1, "valor": "R$ 1.400", "bairro": "IPIRANGA", "cidade": "Sao Paulo", "area": 50, "id": 9529764, "subtipo": 2}, {"suites": 0, "vagas": 1, "quartos": 1, "tipo": 1, "valor": "R$ 3.600", "bairro": "VL OL\u00cdMPIA", "cidade": "Sao Paulo", "area": 43, "id": 9585864, "subtipo": 1}, {"suites": 0, "vagas": 1, "quartos": 3, "tipo": 1, "valor": "R$ 1.550", "bairro": "PIRITUBA", "cidade": "Sao Paulo", "area": 50, "id": 9452304, "subtipo": 1}, {"suites": 1, "vagas": 1, "quartos": 1, "tipo": 1, "valor": "R$ 4.300", "bairro": "VL OL\u00cdMPIA", "cidade": "Sao Paulo", "area": 65, "id": 9242825, "subtipo": 4}, {"suites": 0, "vagas": 1, "quartos": 2, "tipo": 1, "valor": "R$ 2.000", "bairro": "JD GUEDALA", "cidade": "Sao Paulo", "area": 85, "id": 8648449, "subtipo": 1}, {"suites": 1, "vagas": 1, "quartos": 1, "tipo": 1, "valor": "R$ 3.800", "bairro": "MOEMA", "cidade": "Sao Paulo", "area": 50, "id": 9329043, "subtipo": 2}, {"suites": 3, "vagas": 4, "quartos": 4, "tipo": 1, "valor": "R$ 8.500", "bairro": "CAMPO BELO", "cidade": "Sao Paulo", "area": 193, "id": 8858346, "subtipo": 1}, {"suites": 1, "vagas": 2, "quartos": 3, "tipo": 1, "valor": "R$ 3.300", "bairro": "VL LEOPOLDINA", "cidade": "Sao Paulo", "area": 95, "id": 9470110, "subtipo": 1}, {"suites": 2, "vagas": 3, "quartos": 4, "tipo": 1, "valor": "R$ 29.900", "bairro": "VL NOVA CONCEI\u00c7\u00c3O", "cidade": "Sao Paulo", "area": 260, "id": 4349853, "subtipo": 4}, {"suites": 0, "vagas": 1, "quartos": 2, "tipo": 1, "valor": "R$ 2.200", "bairro": "PINHEIROS", "cidade": "Sao Paulo", "area": 60, "id": 8718915, "subtipo": 1}, {"suites": 1, "vagas": 1, "quartos": 1, "tipo": 1, "valor": "R$ 2.850", "bairro": "BELA VISTA", "cidade": "Sao Paulo", "area": 50, "id": 9569661, "subtipo": 2}, {"suites": 1, "vagas": 1, "quartos": 3, "tipo": 1, "valor": "R$ 3.000", "bairro": "PQ MOOCA", "cidade": "Sao Paulo", "area": 132, "id": 9436741, "subtipo": 4}, {"suites": 0, "vagas": 0, "quartos": 2, "tipo": 1, "valor": "R$ 1.700", "bairro": "VL MARIANA", "cidade": "Sao Paulo", "area": 60, "id": 9615069, "subtipo": 1}, {"suites": 1, "vagas": 3, "quartos": 2, "tipo": 1, "valor": "R$ 7.000", "bairro": "PINHEIROS", "cidade": "Sao Paulo", "area": 230, "id": 1248520, "subtipo": 1}, {"suites": 0, "vagas": 1, "quartos": 2, "tipo": 1, "valor": "R$ 2.330", "bairro": "JD AEROPORTO", "cidade": "Sao Paulo", "area": 60, "id": 7807509, "subtipo": 1}]