[{"suites": 1, "vagas": 2, "quartos": 3, "tipo": 1, "valor": "R$ 4.900", "bairro": "JD PAULISTA", "cidade": "Sao Paulo", "area": 142, "id": 8138876, "subtipo": 4}, {"suites": 0, "vagas": 1, "quartos": 1, "tipo": 1, "valor": "R$ 1.900", "bairro": "CONSOLA\u00c7\u00c3O", "cidade": "Sao Paulo", "area": 45, "id": 9609386, "subtipo": 2}, {"suites": 0, "vagas": 1, "quartos": 2, "tipo": 1, "valor": "R$ 1.200", "bairro": "RIO PEQUENO", "cidade": "Sao Paulo", "area": 70, "id": 9047473, "subtipo": 4}, {"suites": 0, "vagas": 1, "quartos": 1, "tipo": 1, "valor": "R$ 1.700", "bairro": "MOEMA", "cidade": "Sao Paulo", "area": 45, "id": 9390220, "subtipo": 2}, {"suites": 3, "vagas": 2, "quartos": 3, "tipo": 1, "valor": "R$ 4.800", "bairro": "CH KLABIN", "cidade": "Sao Paulo", "area": 133, "id": 2831974, "subtipo": 1}, {"suites": 0, "vagas": 1, "quartos": 2, "tipo": 1, "valor": "R$ 2.200", "bairro": "CERQUEIRA C\u00c9SAR", "cidade": "Sao Paulo", "area": 57, "id": 1156421, "subtipo": 1}, {"suites": 1, "vagas": 1, "quartos": 2, "tipo": 1, "valor": "R$ 3.000", "bairro": "MORUMBI", "cidade": "Sao Paulo", "area": 65, "id": 7363591, "subtipo": 2}, {"suites": 0, "vagas": 2, "quartos": 2, "tipo": 1, "valor": "R$ 3.200", "bairro": "MOEMA", "cidade": "Sao Paulo", "area": 70, "id": 9455801, "subtipo": 1}, {"suites": 0, "vagas": 1, "quartos": 1, "tipo": 1, "valor": "R$ 2.100", "bairro": "VL CRUZEIRO", "cidade": "Sao Paulo", "area": 38, "id": 9621079, "subtipo": 4}, {"suites": 0, "vagas": 1, "quartos": 2, "tipo": 1, "valor": "R$ 1.300", "bairro": "BUTANT\u00c3", "cidade": "Sao Paulo", "area": 60, "id": 7867972, "subtipo": 2}, {"suites": 3, "vagas": 3, "quartos": 4, "tipo": 1, "valor": "R$ 4.500", "bairro": "VL MARIANA", "cidade": "Sao Paulo", "area": 176, "id": 9009199, "subtipo": 1}, {"suites": 1, "vagas": 3, "quartos": 3, "tipo": 1, "valor": "R$ 3.500", "bairro": "PANAMBY", "cidade": "Sao Paulo", "area": 178, "id": 7809135, "subtipo": 1}, {"suites": 1, "vagas": 1, "quartos": 3, "tipo": 1, "valor": "R$ 2.400", "bairro": "VL MARIANA", "cidade": "Sao Paulo", "area": 70, "id": 6894936, "subtipo": 4}, {"suites": 1, "vagas": 2, "quartos": 3, "tipo": 1, "valor": "R$ 7.000", "bairro": "PARA\u00cdSO", "cidade": "Sao Paulo", "area": 305, "id": 9237520, "subtipo": 1}, {"suites": 0, "vagas": 0, "quartos": 1, "tipo": 1, "valor": "R$ 1.500", "bairro": "PQ VIT\u00d3RIA", "cidade": "Sao Paulo", "area": 50, "id": 9350342, "subtipo": 1}, {"suites": 1, "vagas": 0, "quartos": 3, "tipo": 1, "valor": "R$ 1.300", "bairro": "INTERLAGOS", "cidade": "Sao Paulo", "area": 100, "id": 9377583, "subtipo": 1}, {"suites": 3, "vagas": 4, "quartos": 4, "tipo": 1, "valor": "R$ 6.500", "bairro": "CAMPO BELO", "cidade": "Sao Paulo", "area": 290, "id": 4665252, "subtipo": 2}, {"suites": 0, "vagas": 0, "quartos": 1, "tipo": 1, "valor": "R$ 1.400", "bairro": "ACLIMA\u00c7\u00c3O", "cidade": "Sao Paulo", "area": 40, "id": 8880969, "subtipo": 1}]